Workbook
Name Aporte: Planilha1!$D$17
Name Patrimonio: Planilha1!$D$20
Name Qtde_anos: Planilha1!$D$18
Name Rendimento_Carteira: Planilha1!$D$13
Name Salario: Planilha1!$D$12
Name Sugestao: Planilha1!$D$14
Name Taxa_mensal: Planilha1!$D$19
Name Taxa_mensala: Planilha1!$D$19

Sheet Planilha1
B11: Configurações
B12: Salário | D12: 1000
B13: Rendimento da Carteira | D13: 0.0055
B14: Sugestão de Investimento | D14: =D12*0.3 -> 300
B16: Investimento Mensal
B17: Quanto investir por Mês? | D17: 200
B18: Por quantos anos? | D18: 5
B19: Taxa de rendimento Mensal? | D19: 0.01079
B20: Patrimônio Acumulado | D20: =FV(Taxa_mensal,Qtde_anos*12,Aporte)*-1 -> 16755.383
B21: Dividendos Mensais | D21: =Patrimonio*Rendimento_Carteira -> 92.154605
B23: Cenários | C23: Patrimônio | D23: Dividendo
A24: 2 | B24: Qual o Valor em 2 anos? | C24: =FV(Taxa_mensal,$A24*12,Aporte)*-1 -> 5445.5255 | D24: =C24*Rendimento_Carteira -> 29.95039
A25: 5 | B25: Qual o Valor em 5 anos? | C25: =FV(Taxa_mensal,$A25*12,Aporte)*-1 -> 16755.383 | D25: =C25*Rendimento_Carteira -> 92.154605
A26: 10 | B26: Qual o Valor em 10 anos? | C26: =FV(Taxa_mensal,$A26*12,Aporte)*-1 -> 48656.843 | D26: =C26*Rendimento_Carteira -> 267.61263
A27: 20 | B27: Qual o Valor em 20 anos? | C27: =FV(Taxa_mensal,$A27*12,Aporte)*-1 -> 225039.68 | D27: =C27*Rendimento_Carteira -> 1237.7182
A28: 30 | B28: Qual o Valor em 30 anos? | C28: =FV(Taxa_mensal,$A28*12,Aporte)*-1 -> 864433.93 | D28: =C28*Rendimento_Carteira -> 4754.3866
B31: Perfil | C31: Conservador
B32: Valor a ser Investido por Mês | C32: =Aporte -> 200
B34: Tipo de FII | C34: % Sugerido | D34: Valores
B35: Desenvolvimento | C35: =VLOOKUP($C$31&"-"&B35,Apoio!$B$2:$E$23,4,FALSE) -> 0 | D35: =C35*C32 -> 0
B36: FOF's | C36: =VLOOKUP($C$31&"-"&B36,Apoio!$B$2:$E$23,4,FALSE) -> 0.1 | D36: =C36*$C$32 -> 20
B37: Híbridos | C37: =VLOOKUP($C$31&"-"&B37,Apoio!$B$2:$E$23,4,FALSE) -> 0.1 | D37: =C37*$C$32 -> 20
B38: Hotelarias | C38: =VLOOKUP($C$31&"-"&B38,Apoio!$B$2:$E$23,4,FALSE) -> 0 | D38: =C38*$C$32 -> 0
B39: Logísticos | C39: =VLOOKUP($C$31&"-"&B39,Apoio!$B$2:$E$23,4,FALSE) -> 0.1 | D39: =C39*$C$32 -> 20
B40: Papel | C40: =VLOOKUP($C$31&"-"&B40,Apoio!$B$2:$E$23,4,FALSE) -> 0.3 | D40: =C40*$C$32 -> 60
B41: Tijolo | C41: =VLOOKUP($C$31&"-"&B41,Apoio!$B$2:$E$23,4,FALSE) -> 0.4 | D41: =C41*$C$32 -> 80
B42: Total | D42: =SUM(D35:D41) -> 200

Sheet Apoio
B2: CHAVE | C2: PERFIL | D2: TIPO DE FII | E2: %
B3: =C3&"-"&D3 -> Conservador-Desenvolvimento | C3: Conservador | D3: Desenvolvimento | E3: 0
B4: =C4&"-"&D4 -> Conservador-FOF's | C4: Conservador | D4: FOF's | E4: 0.1
B5: =C5&"-"&D5 -> Conservador-Híbridos | C5: Conservador | D5: Híbridos | E5: 0.1
B6: =C6&"-"&D6 -> Conservador-Hotelarias | C6: Conservador | D6: Hotelarias | E6: 0
B7: =C7&"-"&D7 -> Conservador-Logísticos | C7: Conservador | D7: Logísticos | E7: 0.1
B8: =C8&"-"&D8 -> Conservador-Papel | C8: Conservador | D8: Papel | E8: 0.3
B9: =C9&"-"&D9 -> Conservador-Tijolo | C9: Conservador | D9: Tijolo | E9: 0.4
B10: =C10&"-"&D10 -> Moderado-Desenvolvimento | C10: Moderado | D10: Desenvolvimento | E10: 0.05
B11: =C11&"-"&D11 -> Moderado-FOF's | C11: Moderado | D11: FOF's | E11: 0.1
B12: =C12&"-"&D12 -> Moderado-Híbridos | C12: Moderado | D12: Híbridos | E12: 0.1
B13: =C13&"-"&D13 -> Moderado-Hotelarias | C13: Moderado | D13: Hotelarias | E13: 0.05
B14: =C14&"-"&D14 -> Moderado-Logísticos | C14: Moderado | D14: Logísticos | E14: 0.1
... B23: =C23&"-"&D23 -> Agressivo-Tijolo | C23: Agressivo | D23: Tijolo | E23: 0.25
